buffalo_gym/__init__.py
buffalo_gym/envs/__init__.py
buffalo_gym/envs/boundlessbuffalo_gym.py
buffalo_gym/envs/buffalo_gym.py
buffalo_gym/envs/buffalotrail_gym.py
buffalo_gym/envs/duelingbuffalo_gym.py
buffalo_gym/envs/fatiguebandit_gym.py
buffalo_gym/envs/multibuffalo_gym.py
buffalo_gym/envs/symbolicstate_gym.py
buffalo_gym/utils/__init__.py
buffalo_gym/utils/utils.py
buffalo_gym-0.4.0.dist-info/licenses/license.txt
buffalo_gym-0.4.0.dist-info/METADATA
buffalo_gym-0.4.0.dist-info/WHEEL
buffalo_gym-0.4.0.dist-info/top_level.txt
buffalo_gym-0.4.0.dist-info/RECORD
