Metadata-Version: 2.4
Name: buffalo_gym
Version: 0.4.0
Summary: Buffalo Gym environment
Author: foreverska
Project-URL: Github:, https://github.com/foreverska/buffalo-gym
Keywords: gymnasium,gym
License-File: license.txt
Requires-Dist: gymnasium>=0.26.0
Requires-Dist: numpy
Dynamic: author
Dynamic: description
Dynamic: description-content-type
Dynamic: keywords
Dynamic: license-file
Dynamic: project-url
Dynamic: requires-dist
Dynamic: summary
